[
  {
    "version": "0.1.0-alpha.5",
    "title": "0.1.0-alpha.5",
    "aliases": [
      "latest",
      "unstable"
    ]
  },
  {
    "version": "0.1.0-alpha.4",
    "title": "0.1.0-alpha.4",
    "aliases": []
  },
  {
    "version": "0.1.0-alpha.3",
    "title": "0.1.0-alpha.3",
    "aliases": []
  },
  {
    "version": "0.1.0-alpha.2",
    "title": "0.1.0-alpha.2",
    "aliases": []
  },
  {
    "version": "0.1.0-alpha.1",
    "title": "0.1.0-alpha.1",
    "aliases": []
  },
  {
    "version": "0.1.0-alpha",
    "title": "0.1.0-alpha",
    "aliases": []
  }
]
